requirements.txt
gtfparse/__init__.py
gtfparse/attribute_parsing.py
gtfparse/create_missing_features.py
gtfparse/parsing_error.py
gtfparse/read_gtf.py
gtfparse-2.5.0.dist-info/LICENSE
gtfparse-2.5.0.dist-info/METADATA
gtfparse-2.5.0.dist-info/WHEEL
gtfparse-2.5.0.dist-info/top_level.txt
gtfparse-2.5.0.dist-info/RECORD
