Metadata-Version: 2.1
Name: gtfparse
Version: 2.5.0
Summary: Parsing library for extracting data frames of genomic features from GTF files
Author-email: Alex Rubinsteyn <alex.rubinsteyn@unc.edu>
Project-URL: Homepage, https://github.com/openvax/gtfparse
Project-URL: Bug Tracker, https://github.com/openvax/gtfparse
Classifier: Development Status :: 4 - Beta
Classifier: Environment :: Console
Classifier: Operating System :: OS Independent
Classifier: Intended Audience :: Science/Research
Classifier: License :: OSI Approved :: Apache Software License
Classifier: Programming Language :: Python
Classifier: Topic :: Scientific/Engineering :: Bio-Informatics
Requires-Python: >=3.7
License-File: LICENSE
Requires-Dist: polars<0.21.0,>=0.20.2
Requires-Dist: pyarrow<14.1.0,>=14.0.2
